<?xml version="1.0" encoding="utf-8" ?><dwsync><file name="style.css" server="ftpcluster.loopia.se" local="3416387168" remote="12006393692" /><file name="passwordChecker.js" server="ftpcluster.loopia.se" local="3416494976" remote="12006859472" /><file name="testconect.php" server="ftpcluster.loopia.se" local="3416462655" remote="12006393692" /><file name="ajaxPrototype.js" server="ftpcluster.loopia.se" local="3416933374" remote="12006865832" /><file name="ajaxPrototype2.js" server="ftpcluster.loopia.se" local="3416934737" remote="12006865832" /><file name="ajaxTest.css" server="ftpcluster.loopia.se" local="3415894988" remote="12006865832" /><file name="ajxCon.js" server="ftpcluster.loopia.se" local="3416494782" remote="12006865832" /><file name="explaination" server="ftpcluster.loopia.se" local="3416408678" remote="12006865832" /><file name="func.js" server="ftpcluster.loopia.se" local="3416208731" remote="12006865832" /><file name="index.html" server="ftpcluster.loopia.se" local="3416412736" remote="12006865832" /><file name="susPhp.php" server="ftpcluster.loopia.se" local="3416933961" remote="12006865832" /><file name="testPhp1.php" server="ftpcluster.loopia.se" local="3416464035" remote="12006865832" /><file name="activation.php" server="ftpcluster.loopia.se" local="3416933331" remote="12006865832" /></dwsync>